pysqlitecrypto_rsa/__init__.py
pysqlitecrypto_rsa/encryption_operations.py
pysqlitecrypto_rsa/keychain_operations.py
pysqlitecrypto_rsa-0.2.2.dist-info/LICENSE
pysqlitecrypto_rsa-0.2.2.dist-info/METADATA
pysqlitecrypto_rsa-0.2.2.dist-info/WHEEL
pysqlitecrypto_rsa-0.2.2.dist-info/entry_points.txt
pysqlitecrypto_rsa-0.2.2.dist-info/top_level.txt
pysqlitecrypto_rsa-0.2.2.dist-info/RECORD
