Metadata-Version: 2.1
Name: pysqlitecrypto-rsa
Version: 0.2.2
Summary: A package for RSA encryption and decryption using SQLite storage.
Home-page: https://github.com/hecdelatorre/Pysqlitecrypto-RSA.git
Author: hecdelatorre
Author-email: hector982015@gmail.com
License: GPL-3.0
Keywords: RSA encryption decryption SQLite cryptography
License-File: LICENSE
Requires-Dist: rsa
